django_orgs/__init__.py
django_orgs/apps.py
django_orgs/conf.py
django_orgs/models.py
django_orgs/services.py
django_orgs/migrations/0001_initial.py
django_orgs/migrations/__init__.py
django_orgs-0.0.2.dist-info/METADATA
django_orgs-0.0.2.dist-info/WHEEL
django_orgs-0.0.2.dist-info/RECORD
